{
"CPU": 2.208835,
"Starttime": 1715001162,
"Epoch": 1715165982,
"Version": "0.8",
"Throttled": 28,
"Utilization": 72.727272,
"Connections": 2,
"NodesCount": 11,
"TasksNew": 3,
"TasksCompleted": 5,
"TasksRunning": 8,
"TasksFailed": 0,
"TasksCount": 16,
"Tasks":[
{
"ID": 54145,
"Binary": "BTC_LOTTERY",
"State": 2,
"Progress": 0,
"Start": 1715165652,
"End": 0
}
,
{
"ID": 54146,
"Binary": "BTC_LOTTERY",
"State": 2,
"Progress": 0,
"Start": 1715165751,
"End": 0
}
,
{
"ID": 54147,
"Binary": "BTC_LOTTERY",
"State": 2,
"Progress": 0,
"Start": 1715165715,
"End": 0
}
,
{
"ID": 54148,
"Binary": "BTC_LOTTERY",
"State": 4,
"Progress": 100,
"Start": 1715165863,
"End": 1715165933
}
,
{
"ID": 54149,
"Binary": "BTC_LOTTERY",
"State": 4,
"Progress": 100,
"Start": 1715165765,
"End": 1715165957
}
,
{
"ID": 54150,
"Binary": "BTC_LOTTERY",
"State": 2,
"Progress": 0,
"Start": 1715165740,
"End": 0
}
,
{
"ID": 54153,
"Binary": "BTC_LOTTERY",
"State": 2,
"Progress": 0,
"Start": 1715165594,
"End": 0
}
,
{
"ID": 54166,
"Binary": "HELIUM_MNEMONICS",
"State": 4,
"Progress": 100,
"Start": 1715165813,
"End": 1715165977
}
,
{
"ID": 54167,
"Binary": "HELIUM_MNEMONICS",
"State": 4,
"Progress": 100,
"Start": 1715165813,
"End": 1715165973
}
,
{
"ID": 54169,
"Binary": "HELIUM_MNEMONICS",
"State": 1,
"Progress": 0,
"Start": 0,
"End": 0
}
,
{
"ID": 54170,
"Binary": "HELIUM_MNEMONICS",
"State": 1,
"Progress": 0,
"Start": 0,
"End": 0
}
,
{
"ID": 54171,
"Binary": "HELIUM_MNEMONICS",
"State": 2,
"Progress": 0,
"Start": 1715165976,
"End": 0
}
,
{
"ID": 54172,
"Binary": "HELIUM_MNEMONICS",
"State": 2,
"Progress": 0,
"Start": 1715165973,
"End": 0
}
,
{
"ID": 54173,
"Binary": "HELIUM_MNEMONICS",
"State": 1,
"Progress": 0,
"Start": 0,
"End": 0
}
,
{
"ID": 54174,
"Binary": "HELIUM_MNEMONICS",
"State": 4,
"Progress": 100,
"Start": 1715165899,
"End": 1715165976
}
,
{
"ID": 54175,
"Binary": "HELIUM_MNEMONICS",
"State": 2,
"Progress": 0,
"Start": 1715165977,
"End": 0
}
],
"Nodes":[
{
"ID": "AWHITE",
"Class": 1,
"Task": 54147,
"CPUCount": 8,
"LoadAverage": 0.000000,
"TasksCompleted": 162,
"System": 7,
"Enabled": 1
}
,
{
"ID": "J_PROX",
"Class": 1,
"Task": 54150,
"CPUCount": 2,
"LoadAverage": 4.000000,
"TasksCompleted": 114,
"System": 5,
"Enabled": 1
}
,
{
"ID": "J_PROX",
"Class": 1,
"Task": 54146,
"CPUCount": 2,
"LoadAverage": 4.000000,
"TasksCompleted": 113,
"System": 5,
"Enabled": 1
}
,
{
"ID": "GS_EXPLORER",
"Class": 1,
"Task": 0,
"CPUCount": 1,
"LoadAverage": 0.730000,
"TasksCompleted": 105,
"System": 5,
"Enabled": 1
}
,
{
"ID": "GS_API",
"Class": 1,
"Task": 54153,
"CPUCount": 1,
"LoadAverage": 2.000000,
"TasksCompleted": 96,
"System": 5,
"Enabled": 1
}
,
{
"ID": "GS_WORK",
"Class": 1,
"Task": 54145,
"CPUCount": 1,
"LoadAverage": 2.000000,
"TasksCompleted": 98,
"System": 5,
"Enabled": 1
}
,
{
"ID": "L2_PROD",
"Class": 1,
"Task": 0,
"CPUCount": 2,
"LoadAverage": 1.590000,
"TasksCompleted": 116,
"System": 5,
"Enabled": 1
}
,
{
"ID": "PI_KNS",
"Class": 1,
"Task": 54172,
"CPUCount": 4,
"LoadAverage": 4.300000,
"TasksCompleted": 107,
"System": 6,
"Enabled": 1
}
,
{
"ID": "PI_KNS",
"Class": 1,
"Task": 54175,
"CPUCount": 4,
"LoadAverage": 4.300000,
"TasksCompleted": 107,
"System": 6,
"Enabled": 1
}
,
{
"ID": "ABLACK",
"Class": 1,
"Task": 54171,
"CPUCount": 3,
"LoadAverage": 11.130000,
"TasksCompleted": 64,
"System": 6,
"Enabled": 1
}
,
{
"ID": "LibClient",
"Class": 2,
"Task": 0,
"CPUCount": 1,
"LoadAverage": 0.009277,
"TasksCompleted": 0,
"System": 5,
"Enabled": 1
}
,
{
"ID": "LibClient",
"Class": 2,
"Task": 0,
"CPUCount": 1,
"LoadAverage": 0.009277,
"TasksCompleted": 0,
"System": 5,
"Enabled": 1
}
,
{
"ID": "IMAC1",
"Class": 1,
"Task": 0,
"CPUCount": 8,
"LoadAverage": 1.728516,
"TasksCompleted": 1,
"System": 3,
"Enabled": 1
}
]}