{
"CPU": 1.424024,
"Starttime": 1715001162,
"Epoch": 1715002182,
"Version": "0.8",
"Throttled": 0,
"Utilization": 0.000000,
"Connections": 2,
"NodesCount": 6,
"TasksNew": 0,
"TasksCompleted": 15,
"TasksRunning": 0,
"TasksFailed": 0,
"TasksCount": 15,
"Tasks":[
{
"ID": 42976,
"Binary": "DGLTC_LOTTERY",
"State": 4,
"Progress": 100,
"Start": 1715002138,
"End": 1715002140
}
,
{
"ID": 42977,
"Binary": "DGLTC_LOTTERY",
"State": 4,
"Progress": 100,
"Start": 1715002138,
"End": 1715002140
}
,
{
"ID": 42978,
"Binary": "DGLTC_LOTTERY",
"State": 4,
"Progress": 100,
"Start": 1715002138,
"End": 1715002141
}
,
{
"ID": 42979,
"Binary": "DGLTC_LOTTERY",
"State": 4,
"Progress": 100,
"Start": 1715002138,
"End": 1715002141
}
,
{
"ID": 42980,
"Binary": "DGLTC_LOTTERY",
"State": 4,
"Progress": 100,
"Start": 1715002140,
"End": 1715002142
}
,
{
"ID": 42981,
"Binary": "DGLTC_LOTTERY",
"State": 4,
"Progress": 100,
"Start": 1715002151,
"End": 1715002153
}
,
{
"ID": 42982,
"Binary": "DGLTC_LOTTERY",
"State": 4,
"Progress": 100,
"Start": 1715002151,
"End": 1715002153
}
,
{
"ID": 42983,
"Binary": "DGLTC_LOTTERY",
"State": 4,
"Progress": 100,
"Start": 1715002151,
"End": 1715002153
}
,
{
"ID": 42984,
"Binary": "DGLTC_LOTTERY",
"State": 4,
"Progress": 100,
"Start": 1715002151,
"End": 1715002153
}
,
{
"ID": 42985,
"Binary": "DGLTC_LOTTERY",
"State": 4,
"Progress": 100,
"Start": 1715002153,
"End": 1715002155
}
,
{
"ID": 42986,
"Binary": "DGLTC_LOTTERY",
"State": 4,
"Progress": 100,
"Start": 1715002158,
"End": 1715002160
}
,
{
"ID": 42987,
"Binary": "DGLTC_LOTTERY",
"State": 4,
"Progress": 100,
"Start": 1715002158,
"End": 1715002160
}
,
{
"ID": 42988,
"Binary": "DGLTC_LOTTERY",
"State": 4,
"Progress": 100,
"Start": 1715002158,
"End": 1715002161
}
,
{
"ID": 42989,
"Binary": "DGLTC_LOTTERY",
"State": 4,
"Progress": 100,
"Start": 1715002158,
"End": 1715002160
}
,
{
"ID": 42990,
"Binary": "DGLTC_LOTTERY",
"State": 4,
"Progress": 100,
"Start": 1715002160,
"End": 1715002162
}
],
"Nodes":[
{
"ID": "PI_KNS",
"Class": 1,
"Task": 0,
"CPUCount": 4,
"LoadAverage": 0.510000,
"TasksCompleted": 1,
"System": 6,
"Enabled": 1
}
,
{
"ID": "PI_KNS",
"Class": 1,
"Task": 0,
"CPUCount": 4,
"LoadAverage": 0.510000,
"TasksCompleted": 1,
"System": 6,
"Enabled": 1
}
,
{
"ID": "GS_WORK",
"Class": 1,
"Task": 0,
"CPUCount": 1,
"LoadAverage": 0.120000,
"TasksCompleted": 18,
"System": 5,
"Enabled": 1
}
,
{
"ID": "GS_EXPLORER",
"Class": 1,
"Task": 0,
"CPUCount": 1,
"LoadAverage": 0.090000,
"TasksCompleted": 21,
"System": 5,
"Enabled": 1
}
,
{
"ID": "J_PROX",
"Class": 1,
"Task": 0,
"CPUCount": 2,
"LoadAverage": 0.252930,
"TasksCompleted": 31,
"System": 5,
"Enabled": 1
}
,
{
"ID": "J_PROX",
"Class": 1,
"Task": 0,
"CPUCount": 2,
"LoadAverage": 0.252930,
"TasksCompleted": 31,
"System": 5,
"Enabled": 1
}
,
{
"ID": "LibClient",
"Class": 2,
"Task": 0,
"CPUCount": 1,
"LoadAverage": 0.094238,
"TasksCompleted": 0,
"System": 5,
"Enabled": 1
}
,
{
"ID": "LibClient",
"Class": 2,
"Task": 0,
"CPUCount": 1,
"LoadAverage": 0.086426,
"TasksCompleted": 0,
"System": 5,
"Enabled": 1
}
]}