{
"CPU": 1.371926,
"Starttime": 1715001162,
"Epoch": 1715051982,
"Version": "0.8",
"Throttled": 15,
"Utilization": 45.454548,
"Connections": 2,
"NodesCount": 11,
"TasksNew": 0,
"TasksCompleted": 0,
"TasksRunning": 5,
"TasksFailed": 0,
"TasksCount": 5,
"Tasks":[
{
"ID": 47476,
"Binary": "DGLTC_LOTTERY",
"State": 2,
"Progress": 0,
"Start": 1715051981,
"End": 0
}
,
{
"ID": 47477,
"Binary": "DGLTC_LOTTERY",
"State": 2,
"Progress": 0,
"Start": 1715051981,
"End": 0
}
,
{
"ID": 47478,
"Binary": "DGLTC_LOTTERY",
"State": 2,
"Progress": 0,
"Start": 1715051981,
"End": 0
}
,
{
"ID": 47479,
"Binary": "DGLTC_LOTTERY",
"State": 2,
"Progress": 0,
"Start": 1715051981,
"End": 0
}
,
{
"ID": 47480,
"Binary": "DGLTC_LOTTERY",
"State": 2,
"Progress": 0,
"Start": 1715051981,
"End": 0
}
],
"Nodes":[
{
"ID": "GS_WORK",
"Class": 1,
"Task": 0,
"CPUCount": 1,
"LoadAverage": 0.050000,
"TasksCompleted": 745,
"System": 5,
"Enabled": 1
}
,
{
"ID": "GS_EXPLORER",
"Class": 1,
"Task": 47477,
"CPUCount": 1,
"LoadAverage": 0.060000,
"TasksCompleted": 746,
"System": 5,
"Enabled": 1
}
,
{
"ID": "J_PROX",
"Class": 1,
"Task": 47479,
"CPUCount": 2,
"LoadAverage": 0.000000,
"TasksCompleted": 930,
"System": 5,
"Enabled": 1
}
,
{
"ID": "J_PROX",
"Class": 1,
"Task": 47480,
"CPUCount": 2,
"LoadAverage": 0.000000,
"TasksCompleted": 912,
"System": 5,
"Enabled": 1
}
,
{
"ID": "LibClient",
"Class": 2,
"Task": 0,
"CPUCount": 1,
"LoadAverage": 0.120605,
"TasksCompleted": 0,
"System": 5,
"Enabled": 1
}
,
{
"ID": "ABLACK",
"Class": 1,
"Task": 0,
"CPUCount": 1,
"LoadAverage": 9.040000,
"TasksCompleted": 38,
"System": 6,
"Enabled": 1
}
,
{
"ID": "AWHITE",
"Class": 1,
"Task": 0,
"CPUCount": 8,
"LoadAverage": 0.000000,
"TasksCompleted": 37,
"System": 7,
"Enabled": 1
}
,
{
"ID": "GS_API",
"Class": 1,
"Task": 47476,
"CPUCount": 1,
"LoadAverage": 0.000000,
"TasksCompleted": 422,
"System": 5,
"Enabled": 1
}
,
{
"ID": "L2_PROD",
"Class": 1,
"Task": 47478,
"CPUCount": 2,
"LoadAverage": 0.110000,
"TasksCompleted": 498,
"System": 5,
"Enabled": 1
}
,
{
"ID": "LibClient",
"Class": 2,
"Task": 0,
"CPUCount": 1,
"LoadAverage": 0.120605,
"TasksCompleted": 0,
"System": 5,
"Enabled": 1
}
,
{
"ID": "PI_KNS",
"Class": 1,
"Task": 0,
"CPUCount": 4,
"LoadAverage": 0.360000,
"TasksCompleted": 4,
"System": 6,
"Enabled": 1
}
,
{
"ID": "PI_KNS",
"Class": 1,
"Task": 0,
"CPUCount": 4,
"LoadAverage": 0.360000,
"TasksCompleted": 4,
"System": 6,
"Enabled": 1
}
,
{
"ID": "IMAC1",
"Class": 1,
"Task": 0,
"CPUCount": 8,
"LoadAverage": 7.341797,
"TasksCompleted": 0,
"System": 3,
"Enabled": 1
}
]}