{
"CPU": 2.155388,
"Starttime": 1715001162,
"Epoch": 1715180982,
"Version": "0.8",
"Throttled": 31,
"Utilization": 100.000000,
"Connections": 2,
"NodesCount": 11,
"TasksNew": 13,
"TasksCompleted": 2,
"TasksRunning": 11,
"TasksFailed": 0,
"TasksCount": 26,
"Tasks":[
{
"ID": 54927,
"Binary": "HELIUM_MNEMONICS",
"State": 2,
"Progress": 0,
"Start": 1715180937,
"End": 0
}
,
{
"ID": 54930,
"Binary": "HELIUM_MNEMONICS",
"State": 2,
"Progress": 0,
"Start": 1715180948,
"End": 0
}
,
{
"ID": 54932,
"Binary": "HELIUM_MNEMONICS",
"State": 4,
"Progress": 100,
"Start": 1715180785,
"End": 1715180937
}
,
{
"ID": 54934,
"Binary": "HELIUM_MNEMONICS",
"State": 1,
"Progress": 0,
"Start": 0,
"End": 0
}
,
{
"ID": 54935,
"Binary": "HELIUM_MNEMONICS",
"State": 4,
"Progress": 100,
"Start": 1715180785,
"End": 1715180948
}
,
{
"ID": 54968,
"Binary": "BTC_LOTTERY",
"State": 1,
"Progress": 0,
"Start": 0,
"End": 0
}
,
{
"ID": 54976,
"Binary": "BTC_LOTTERY",
"State": 2,
"Progress": 0,
"Start": 1715180888,
"End": 0
}
,
{
"ID": 54977,
"Binary": "BTC_LOTTERY",
"State": 2,
"Progress": 0,
"Start": 1715180888,
"End": 0
}
,
{
"ID": 54978,
"Binary": "BTC_LOTTERY",
"State": 2,
"Progress": 0,
"Start": 1715180888,
"End": 0
}
,
{
"ID": 54979,
"Binary": "BTC_LOTTERY",
"State": 2,
"Progress": 0,
"Start": 1715180888,
"End": 0
}
,
{
"ID": 54980,
"Binary": "BTC_LOTTERY",
"State": 2,
"Progress": 0,
"Start": 1715180888,
"End": 0
}
,
{
"ID": 54981,
"Binary": "BTC_LOTTERY",
"State": 2,
"Progress": 0,
"Start": 1715180888,
"End": 0
}
,
{
"ID": 54982,
"Binary": "BTC_LOTTERY",
"State": 2,
"Progress": 0,
"Start": 1715180888,
"End": 0
}
,
{
"ID": 54983,
"Binary": "BTC_LOTTERY",
"State": 2,
"Progress": 0,
"Start": 1715180888,
"End": 0
}
,
{
"ID": 54984,
"Binary": "BTC_LOTTERY",
"State": 2,
"Progress": 0,
"Start": 1715180889,
"End": 0
}
,
{
"ID": 54985,
"Binary": "BTC_LOTTERY",
"State": 1,
"Progress": 0,
"Start": 0,
"End": 0
}
,
{
"ID": 54986,
"Binary": "BTC_LOTTERY",
"State": 1,
"Progress": 0,
"Start": 0,
"End": 0
}
,
{
"ID": 54987,
"Binary": "BTC_LOTTERY",
"State": 1,
"Progress": 0,
"Start": 0,
"End": 0
}
,
{
"ID": 54988,
"Binary": "BTC_LOTTERY",
"State": 1,
"Progress": 0,
"Start": 0,
"End": 0
}
,
{
"ID": 54989,
"Binary": "BTC_LOTTERY",
"State": 1,
"Progress": 0,
"Start": 0,
"End": 0
}
,
{
"ID": 54990,
"Binary": "BTC_LOTTERY",
"State": 1,
"Progress": 0,
"Start": 0,
"End": 0
}
,
{
"ID": 54991,
"Binary": "BTC_LOTTERY",
"State": 1,
"Progress": 0,
"Start": 0,
"End": 0
}
,
{
"ID": 54992,
"Binary": "BTC_LOTTERY",
"State": 1,
"Progress": 0,
"Start": 0,
"End": 0
}
,
{
"ID": 54993,
"Binary": "BTC_LOTTERY",
"State": 1,
"Progress": 0,
"Start": 0,
"End": 0
}
,
{
"ID": 54994,
"Binary": "BTC_LOTTERY",
"State": 1,
"Progress": 0,
"Start": 0,
"End": 0
}
,
{
"ID": 54995,
"Binary": "BTC_LOTTERY",
"State": 1,
"Progress": 0,
"Start": 0,
"End": 0
}
],
"Nodes":[
{
"ID": "AWHITE",
"Class": 1,
"Task": 54984,
"CPUCount": 8,
"LoadAverage": 0.000000,
"TasksCompleted": 247,
"System": 7,
"Enabled": 1
}
,
{
"ID": "J_PROX",
"Class": 1,
"Task": 54983,
"CPUCount": 2,
"LoadAverage": 4.000000,
"TasksCompleted": 164,
"System": 5,
"Enabled": 1
}
,
{
"ID": "J_PROX",
"Class": 1,
"Task": 54976,
"CPUCount": 2,
"LoadAverage": 4.000000,
"TasksCompleted": 164,
"System": 5,
"Enabled": 1
}
,
{
"ID": "GS_EXPLORER",
"Class": 1,
"Task": 54978,
"CPUCount": 1,
"LoadAverage": 1.970000,
"TasksCompleted": 146,
"System": 5,
"Enabled": 1
}
,
{
"ID": "GS_API",
"Class": 1,
"Task": 54977,
"CPUCount": 1,
"LoadAverage": 2.000000,
"TasksCompleted": 138,
"System": 5,
"Enabled": 1
}
,
{
"ID": "GS_WORK",
"Class": 1,
"Task": 54982,
"CPUCount": 1,
"LoadAverage": 2.020000,
"TasksCompleted": 137,
"System": 5,
"Enabled": 1
}
,
{
"ID": "L2_PROD",
"Class": 1,
"Task": 54981,
"CPUCount": 2,
"LoadAverage": 3.460000,
"TasksCompleted": 175,
"System": 5,
"Enabled": 1
}
,
{
"ID": "PI_KNS",
"Class": 1,
"Task": 54930,
"CPUCount": 4,
"LoadAverage": 4.900000,
"TasksCompleted": 189,
"System": 6,
"Enabled": 1
}
,
{
"ID": "PI_KNS",
"Class": 1,
"Task": 54927,
"CPUCount": 4,
"LoadAverage": 4.900000,
"TasksCompleted": 188,
"System": 6,
"Enabled": 1
}
,
{
"ID": "LibClient",
"Class": 2,
"Task": 0,
"CPUCount": 1,
"LoadAverage": 3.490723,
"TasksCompleted": 0,
"System": 5,
"Enabled": 1
}
,
{
"ID": "LibClient",
"Class": 2,
"Task": 0,
"CPUCount": 1,
"LoadAverage": 3.446289,
"TasksCompleted": 0,
"System": 5,
"Enabled": 1
}
,
{
"ID": "P_PROX",
"Class": 1,
"Task": 54979,
"CPUCount": 2,
"LoadAverage": 3.490723,
"TasksCompleted": 1,
"System": 5,
"Enabled": 1
}
,
{
"ID": "P_PROX",
"Class": 1,
"Task": 54980,
"CPUCount": 2,
"LoadAverage": 3.490723,
"TasksCompleted": 1,
"System": 5,
"Enabled": 1
}
]}